{
  "address": "https://www.pinterest.com/pin/822892163200209868/",
  "dataMode": "json",
  "hotlinkProtected": false,
  "connectionTimeOut": -1,
  "otherPropertiesMap": {
    "CustomFolderName": "Symphony_Sonata/_created",
    "CustomFileName": "822892163200209868",
    "FileExtensionHandleMethod": "workoutExtension",
    "_json": {
      "id": "822892163200209868",
      "url": "https://www.pinterest.com/pin/822892163200209868/",
      "type": "pin",
      "title": "SHIP DYNAMIC",
      "gridTitle": "SHIP DYNAMIC",
      "description": "charlie and cordelia core",
      "isStoryPin": true,
      "isCarousel": false,
      "doneByMe": false,
      "favouritedByMe": false,
      "isRepin": false,
      "storyPinItemCount": 1,
      "carouselItemCount": 0,
      "repinCount": 416,
      "favouriteUserCount": -1,
      "creator": {
        "username": "Symphony_Sonata",
        "url": "https://www.pinterest.com/Symphony_Sonata/",
        "name": "Symphony Sonata",
        "icon": "https://i.pinimg.com/140x140_RS/de/dd/7f/dedd7fb60f9e6c09779a47a577fdb1eb.jpg"
      },
      "board": {
        "url": "https://www.pinterest.com/Symphony_Sonata/habromania/",
        "name": "HABROMANIA",
        "type": "board",
        "ownerUsername": "Symphony_Sonata",
        "ownerName": "Symphony Sonata",
        "ownerUrl": "https://www.pinterest.com/Symphony_Sonata/",
        "ownerIcon": "https://i.pinimg.com/140x140_RS/de/dd/7f/dedd7fb60f9e6c09779a47a577fdb1eb.jpg"
      },
      "media": [
        {
          "url": "https://i.pinimg.com/originals/8c/08/eb/8c08ebf9ea561bf3204b99e087e3f742.jpg",
          "type": "image"
        }
      ]
    }
  }
}